[
  {"line": 1, "text": "У него жена Ирина Иванова", "numbers": ["31", "44"]},
  {"line": 2, "text": "дочь", "numbers": []},
  {"line": 3, "text": "У нихъ дѣти написанные", "numbers": []},
  {"line": 4, "text": "въ послѣднюю предъ симъ ре", "numbers": []},
  {"line": 5, "text": "визію", "numbers": []},
  {"line": 6, "text": "Михаилъ", "numbers": ["2", "умре въ 794 году"]},
  {"line": 7, "text": "Дочь", "numbers": []},
  {"line": 8, "text": "Ульяна", "numbers": []},
  {"line": 9, "text": "Выдана въ замужество того жъ", "numbers": []},
  {"line": 10, "text": "села за казеннаго крестья", "numbers": []},
  {"line": 11, "text": "нина Савву Кирсенка", "numbers": []},
  {"line": 12, "text": "рожденные послѣ ревизіи", "numbers": []},
  {"line": 13, "text": "Иванъ", "numbers": ["5"]},
  {"line": 14, "text": "Дочери", "numbers": []},
  {"line": 15, "text": "Варвара", "numbers": ["8"]},
  {"line": 16, "text": "Христина", "numbers": ["2"]},
  {"line": 17, "text": "Акилина Павлова дочь Шулики", "numbers": []},
  {"line": 18, "text": "ха вдова", "numbers": ["60", "73"]},
  {"line": 19, "text": "У ней сынъ написанный въ по", "numbers": []},
  {"line": 20, "text": "слѣднюю предъ симъ ревизію", "numbers": []},
  {"line": 21, "text": "Никифоръ Павловъ сынъ", "numbers": ["36", "49"]},
  {"line": 22, "text": "У него жена Параскевія", "numbers": []},
  {"line": 23, "text": "Иосифова дочь", "numbers": ["31", "умре въ 793 году"]},
  {"line": 24, "text": "У нихъ дѣти написанные", "numbers": []},
  {"line": 25, "text": "въ послѣднюю предъ симъ", "numbers": []},
  {"line": 26, "text": "ревизію", "numbers": []}
]
